{"date":"2026-06-23","dayNumber":60,"healthStatus":"green","autohealLastRun":"2026-06-23T01:00","backupLastIncremental":"2026-06-21","memorySizeChars":14020,"obsEvents24h":75,"failedTasks24h":0,"modelDriftConsecutiveClean":18,"wardenEscalationPending":false,"incidentsOpen":0,"frameworks":{"AGILE":"L4","ITSM":"L3","GOVERNANCE":"L3","TOM":"L2","MODEL_STRATEGY":"L3","KNOWLEDGE_MGMT":"L2"},"businessStream":{"linkedinAuthFixed":true,"roiWeeklyCronLive":true,"week2LinkedInCampaign":"pending_angie_approval","googleCalendarAuth":"broken_since_jun3","jotformHrdf":"54_days_outstanding"},"chgsSinceLastStandup":["CHG-0736","CHG-0735","CHG-0734","CHG-0733","CHG-0732","CHG-0731","CHG-0730","CHG-0729","CHG-0728","CHG-0727","CHG-0726","CHG-0614"]}
