{
  "lastChecks": {
    "email": "2026-05-01T00:49:11.342Z",
    "calendar": "2026-05-01T00:49:11.342Z",
    "agentHealth": "2026-05-01T05:19:00Z",
    "apiBalance": "2026-05-01T05:19:00Z",
    "taskWatchdog": "2026-05-01T05:19:00Z",
    "memoryMaintenance": "2026-05-01T05:19:00Z",
    "weather": null,
    "dailyClose": "2026-04-30T14:19:00Z"
  },
  "notes": "3:19PM May1 check: Balance $110.64 T0 clear. Health OK. No stalls/alerts/warden-pending. Memory maintenance done \u2014 blog idea added to MEMORY.md. GOG unavailable (email/cal skipped).",
  "gogAccount": "kenmun@ainchors.com"
}
