{
  "generated_at": "2026-06-22T14:46:06.452806+00:00",
  "generated_at_aest": "2026-06-23 00:46 AEST",
  "period_hours": 24,
  "totals": {
    "ERROR": 56,
    "WARN": 29,
    "INFO": 38
  },
  "top_errors": [
    {
      "type": "warden_violation",
      "count": 56
    }
  ],
  "top_warnings": [
    {
      "type": "auto_heal_needs_ken",
      "count": 29
    }
  ],
  "trend": {
    "has_prev_data": true,
    "prev_errors": 70,
    "prev_warns": 11,
    "errors_pct_change": -20.0,
    "warns_pct_change": 163.6
  },
  "worst_hour": {
    "hour": "2026-06-21T17:00Z",
    "cnt": 10
  }
}