{
  "changelog": {
    "loaded_at": "2026-06-19T12:18:41Z",
    "canonical_path": "agent-skills/changelog",
    "skill_file": "SKILL.md",
    "via": "skill-load.sh"
  },
  "pg-sprint-backlog": {
    "loaded_at": "2026-06-19T13:07:09Z",
    "canonical_path": "agent-skills/pg-sprint-backlog",
    "skill_file": "SKILL.md",
    "via": "skill-load.sh"
  },
  "agile": {
    "loaded_at": "2026-06-18T06:40:57Z",
    "canonical_path": "agent-skills/agile",
    "skill_file": "SKILL.md",
    "via": "skill-load.sh"
  },
  "subagent-dispatch": {
    "loaded_at": "2026-06-19T11:21:04Z",
    "canonical_path": "agent-skills/subagent-dispatch",
    "skill_file": "SKILL.md",
    "via": "skill-load.sh"
  },
  "crest": {
    "loaded_at": "2026-06-19T11:39:19Z",
    "canonical_path": "agent-skills/crest",
    "skill_file": "SKILL.md",
    "via": "skill-load.sh"
  },
  "model-routing": {
    "loaded_at": "2026-06-19T12:18:41Z",
    "canonical_path": "agent-skills/model-routing",
    "skill_file": "SKILL.md",
    "via": "skill-load.sh"
  },
  "telegram": {
    "loaded_at": "2026-06-19T00:34:27Z",
    "canonical_path": "agent-skills/telegram",
    "skill_file": "SKILL.md",
    "via": "skill-load.sh"
  }
}